setup.py
JagsGaus/Binomialdistribution.py
JagsGaus/Gaussiandistribution.py
JagsGaus/Generaldistribution.py
JagsGaus/__init__.py
JagsGaus.egg-info/PKG-INFO
JagsGaus.egg-info/SOURCES.txt
JagsGaus.egg-info/dependency_links.txt
JagsGaus.egg-info/not-zip-safe
JagsGaus.egg-info/top_level.txt