Metadata-Version: 1.0
Name: JagsGaus
Version: 1.3
Summary: Gaussian distributions
Home-page: UNKNOWN
Author: Jagriti Prakash
Author-email: UNKNOWN
License: UNKNOWN
Platform: UNKNOWN
